Metadata-Version: 2.1
Name: UncertaintyPlayground
Version: 0.1.2
Summary: A Python library for uncertainty estimation in supervised learning tasks
Home-page: https://github.com/Unco3892/UncertaintyPlayground
Author: Ilia Azizi
Author-email: ilia.azizi@unil.ch
Classifier: Development Status :: 3 - Alpha
Classifier: License :: OSI Approved :: MIT License
Classifier: Programming Language :: Python :: 3
Classifier: Programming Language :: Python :: 3.8
Classifier: Programming Language :: Python :: 3.9
Classifier: Programming Language :: Python :: 3.10
License-File: LICENSE
Requires-Dist: torch (==2.0.1)
Requires-Dist: gpytorch (==1.10)
Requires-Dist: numpy (==1.24.2)
Requires-Dist: scikit-learn (==1.2.2)
Requires-Dist: matplotlib (==3.7.1)
Requires-Dist: seaborn (==0.12.2)
